MANIFEST.in
README.rst
pyproject.toml
setup.py
bindings/python/pulchra_bindings.cpp
bindings/python/pypulchra_bindings.cpp
pypulchra/__init__.py
pypulchra.egg-info/PKG-INFO
pypulchra.egg-info/SOURCES.txt
pypulchra.egg-info/dependency_links.txt
pypulchra.egg-info/entry_points.txt
pypulchra.egg-info/not-zip-safe
pypulchra.egg-info/top_level.txt
src/pulchra.cpp
src/pulchra.hpp