Metadata-Version: 2.1
Name: pypulchra
Version: 1.0.1
Summary: Python bindings for the pulchra CA -> full bb trace library
Home-page: https://github.com/danpf/pulchra
Author: Danny Farrell
Author-email: danpfuw@gmail.com
License: UNKNOWN
Platform: UNKNOWN
Classifier: Development Status :: 5 - Production/Stable
Classifier: Topic :: Scientific/Engineering :: Bio-Informatics
Classifier: Topic :: Scientific/Engineering
Classifier: Programming Language :: Python :: 3.7
Classifier: Programming Language :: Python :: 3.8
Classifier: Programming Language :: Python :: 3.9
Classifier: Programming Language :: Python :: 3.10
Classifier: Programming Language :: Python :: 3.11
Requires-Python: >=3.7
